libasvat/__init__.py
libasvat/command_utils.py
libasvat/data.py
libasvat/git.py
libasvat/google_sheet.py
libasvat/idgen.py
libasvat/logger.py
libasvat/range.py
libasvat/time.py
libasvat/utils.py
libasvat/version.py
libasvat/imgui/__init__.py
libasvat/imgui/colors.py
libasvat/imgui/fonts.py
libasvat/imgui/general.py
libasvat/imgui/math.py
libasvat/imgui/popups.py
libasvat/imgui/sheet.py
libasvat/imgui/windows.py
libasvat/imgui/editors/__init__.py
libasvat/imgui/editors/container.py
libasvat/imgui/editors/controller.py
libasvat/imgui/editors/database.py
libasvat/imgui/editors/editor.py
libasvat/imgui/editors/primitives.py
libasvat/imgui/nodes/__init__.py
libasvat/imgui/nodes/editor.py
libasvat/imgui/nodes/node_config.py
libasvat/imgui/nodes/nodes.py
libasvat/imgui/nodes/nodes_data.py
libasvat-1.2.0.dist-info/licenses/LICENSE
libasvat-1.2.0.dist-info/METADATA
libasvat-1.2.0.dist-info/WHEEL
libasvat-1.2.0.dist-info/top_level.txt
libasvat-1.2.0.dist-info/RECORD
