Metadata-Version: 2.4
Name: libasvat
Version: 1.2.0
Summary: Python library package with a collection of utility modules, from simple general utility functions to more complex IMGUI (imgui-bundle) utility classes.
Home-page: https://github.com/Rewasvat/libasvat
Author: Fernando Omar Aluani
Author-email: Fernando Omar Aluani <rewasvat@gmail.com>
License-Expression: MIT
Project-URL: Homepage, https://github.com/Rewasvat/libasvat
Project-URL: Issues, https://github.com/Rewasvat/libasvat/issues
Classifier: Programming Language :: Python :: 3.13
Classifier: Operating System :: OS Independent
Classifier: Development Status :: 5 - Production/Stable
Requires-Python: >=3.13
License-File: LICENSE
Requires-Dist: setuptools_scm
Requires-Dist: Click>=8.1.0
Requires-Dist: Colorama
Requires-Dist: keyring
Requires-Dist: imgui-bundle
Requires-Dist: debugpy
Requires-Dist: google-api-python-client
Requires-Dist: google-auth-oauthlib
Dynamic: author
Dynamic: home-page
Dynamic: license-file
